kagglefold/__init__.py
kagglefold/alphafold/__init__.py
kagglefold/alphafold/models.py
kagglefold/alphafold/msa.py
kagglefold/batch.py
kagglefold/citations.py
kagglefold/download.py
kagglefold/kagglefold.py
kagglefold/kagglefold_alphafold.py
kagglefold/mmseqs/__init__.py
kagglefold/mmseqs/merge_and_split_msas.py
kagglefold/mmseqs/search.py
kagglefold/mmseqs/split_msas.py
kagglefold/pdb.py
kagglefold/plot.py
kagglefold/utils.py
kagglefold-1.0.dist-info/entry_points.txt
kagglefold-1.0.dist-info/LICENSE
kagglefold-1.0.dist-info/WHEEL
kagglefold-1.0.dist-info/METADATA
kagglefold-1.0.dist-info/RECORD
